pyspark_datasets/__init__.py
pyspark_datasets/_dataframe.py
pyspark_datasets/_schema_utils.py
pyspark_datasets/column.py
pyspark_datasets/dataframe.py
pyspark_datasets/exceptions.py
pyspark_datasets/py.typed
pyspark_datasets-0.1.0.dist-info/licenses/LICENSE
pyspark_datasets-0.1.0.dist-info/METADATA
pyspark_datasets-0.1.0.dist-info/WHEEL
pyspark_datasets-0.1.0.dist-info/top_level.txt
pyspark_datasets-0.1.0.dist-info/RECORD
