Metadata-Version: 2.4
Name: pyspark-datasets
Version: 0.1.0
Summary: Bringing type-checking and schema validation to PySpark DataFrames.
Requires-Python: >=3.10
License-File: LICENSE
Requires-Dist: pyspark
Requires-Dist: sparkdantic
Requires-Dist: exceptiongroup; python_version < "3.11"
Dynamic: license-file
